Metadata-Version: 1.0
Name: distributions-tyler
Version: 0.1
Summary: Gaussian distributions
Home-page: UNKNOWN
Author: Tyler Watkins
Author-email: tylerwatkins101@gmail.com
License: UNKNOWN
Platform: UNKNOWN
